Metadata-Version: 2.1
Name: gsg-utils-stg
Version: 0.0.6
Summary: Library that will contain all utility functions that are accessible by other services.
Home-page: https://bitbucket.org/global-savings-group/pouch-utils-library/src/master/
Author: Pouch-devs
License: Pouch
Platform: UNKNOWN
